README.md
setup.py
django_thaad.egg-info/PKG-INFO
django_thaad.egg-info/SOURCES.txt
django_thaad.egg-info/dependency_links.txt
django_thaad.egg-info/not-zip-safe
django_thaad.egg-info/requires.txt
django_thaad.egg-info/top_level.txt
interceptor/__init__.py
interceptor/admin.py
interceptor/apps.py
interceptor/choices.py
interceptor/interceptor.py
interceptor/models.py
interceptor/tests.py
interceptor/urls.py
interceptor/validators.py
interceptor/views.py
interceptor/api/__init__.py
interceptor/api/fields.py
interceptor/api/permissions.py
interceptor/api/serializers.py
interceptor/api/urls.py
interceptor/api/viewsets.py
interceptor/migrations/0001_initial.py
interceptor/migrations/0002_interceptedrequest_headers.py
interceptor/migrations/0003_interceptedrequest_content_type.py
interceptor/migrations/0004_interceptedfile.py
interceptor/migrations/0005_auto_20200514_0617.py
interceptor/migrations/0006_auto_20200514_0637.py
interceptor/migrations/0007_auto_20200514_0713.py
interceptor/migrations/0008_interceptorsession_session_token.py
interceptor/migrations/0009_interceptormockresponse.py
interceptor/migrations/0010_auto_20200518_0529.py
interceptor/migrations/0011_interceptorsession_creation_date.py
interceptor/migrations/0012_interceptedrequest_matched_response.py
interceptor/migrations/0013_interceptorsession_slug.py
interceptor/migrations/__init__.py