Metadata-Version: 2.1
Name: django-thaad
Version: 1.0.4
Summary: Provide utils to intercept and save/redirect requests
Home-page: UNKNOWN
Author: Luis Moncaris
Author-email: lmoncarisg@gmail.com
License: UNKNOWN
Platform: UNKNOWN
Classifier: Development Status :: 4 - Beta
Classifier: Environment :: Web Environment
Classifier: License :: OSI Approved :: MIT License
Classifier: Natural Language :: English
Classifier: Framework :: Django :: 3.0
Classifier: Intended Audience :: Developers
Classifier: Operating System :: OS Independent
Classifier: Programming Language :: Python
Classifier: Framework :: Django
